main.py
KMLPipePy/CVNodeProcess.py
KMLPipePy/__init__.py
KMLPipePy/api.py
KMLPipePy/base_structs.py
KMLPipePy/types.py
KMLPipePy/operations/__init__.py
KMLPipePy/operations/addInputs.py
KMLPipePy/operations/calcJointAngles.py
KMLPipePy/operations/calcKeyPointVelocities.py
KMLPipePy/operations/clamp.py
KMLPipePy/operations/compareEmbeddings.py
KMLPipePy/operations/compareKPFrames.py
KMLPipePy/operations/conditional.py
KMLPipePy/operations/constant.py
KMLPipePy/operations/createCrop.py
KMLPipePy/operations/createKeyPoint.py
KMLPipePy/operations/createLabel.py
KMLPipePy/operations/crop.py
KMLPipePy/operations/cropBBoxes.py
KMLPipePy/operations/deconstructKeyPoint.py
KMLPipePy/operations/divideInputs.py
KMLPipePy/operations/drawBBoxFrame.py
KMLPipePy/operations/drawKeyPoints.py
KMLPipePy/operations/drawLabel.py
KMLPipePy/operations/drawLabels.py
KMLPipePy/operations/faceMeshDetection.py
KMLPipePy/operations/getKeyPoint.py
KMLPipePy/operations/getVecValue.py
KMLPipePy/operations/kpDist.py
KMLPipePy/operations/multiplyInputs.py
KMLPipePy/operations/normKeyPoints.py
KMLPipePy/operations/normKeyPointsSize.py
KMLPipePy/operations/pose2D.py
KMLPipePy/operations/roboflowClassificationAPI.py
KMLPipePy/operations/roboflowDetect.py
KMLPipePy/operations/roboflowEmbedImages.py
KMLPipePy/operations/roboflowEmbedText.py
KMLPipePy/operations/round.py
KMLPipePy/operations/rtmPose2DBody.py
KMLPipePy/operations/rtmPose2DWholeBody.py
KMLPipePy/operations/setKeyPoint.py
KMLPipePy/operations/setVecValue.py
KMLPipePy/operations/smoothKeyPoints.py
KMLPipePy/operations/smoothVecs.py
KMLPipePy/operations/subtractInputs.py
KMLPipePy/operations/switch.py
KMLPipePy/operations/threeKPAngle.py
KMLPipePy/operations/utils.py
tests/__init__.py
tests/test_drawing_nodes.py
tests/test_kp_nodes.py
tests/test_logic_nodes.py
tests/test_math_nodes.py
tests/test_model_nodes.py
tests/test_rtmpose.py
tests/test_vec_nodes.py
KMLPipePy-1.2.3.dist-info/LICENSE
KMLPipePy-1.2.3.dist-info/METADATA
KMLPipePy-1.2.3.dist-info/WHEEL
KMLPipePy-1.2.3.dist-info/top_level.txt
KMLPipePy-1.2.3.dist-info/RECORD
