Metadata-Version: 2.1
Name: KMLPipePy
Version: 1.2.3
Summary: Official Python library for the Kinetix ML API
Author-email: Maxwell Stone <maxwell@kinetixml.com>, Sammy Taubman <sammy@kinetixml.com>
License: GNU LESSER GENERAL PUBLIC LICENSE
Project-URL: Homepage, https://github.com/kinetix-ml/kml-pipe-py
Keywords: kinetix,ml,api,python,library,wrapper,client
Classifier: License :: OSI Approved :: GNU General Public License v3 (GPLv3)
Classifier: Programming Language :: Python
Classifier: Programming Language :: Python :: 3
Requires-Python: >=3.9
License-File: LICENSE
Requires-Dist: requests
Requires-Dist: numpy
Requires-Dist: opencv-python
Requires-Dist: tensorflow-hub
Requires-Dist: tensorflow
Requires-Dist: roboflow
Requires-Dist: torch
Requires-Dist: chardet
Provides-Extra: dev
Requires-Dist: black ; extra == 'dev'
Requires-Dist: bumpver ; extra == 'dev'
Requires-Dist: isort ; extra == 'dev'
Requires-Dist: pip-tools ; extra == 'dev'
Requires-Dist: pytest ; extra == 'dev'
